Workbook

Sheet 总览
A1: 赴新加坡 NTU 行前面板
A2: 离线版 · 手机上用 Excel / Numbers / WPS 都能打开。只改黄色格子和「清单」表，其他都是公式。
A4: 设置（黄色格子自己改）
A5: 出发日期 | B5: 46327 | C5: 我按「11 intake」推断的，改成你的真实出发日，下面所有日期会重算
A6: 汇率 1 SGD = ? CNY | B6: 5.4 | C6: 默认 5.40，非实时，待核实
A8: 核心指标
A9: 距离出发 | B9: =$B$5-TODAY() | C9: 负数表示已经出发了
A10: 总进度 | B10: =IFERROR(COUNTIFS(清单!$D$2:$D$490,"已完成")/(COUNTA(清单!$C$2:$C$490)-COUNTIF(清单!$D$2:$D$490,"不需要")),0)
A11: 已完成 / 需要做 | B11: =COUNTIFS(清单!$D$2:$D$490,"已完成")&" / "&(COUNTA(清单!$C$2:$C$490)-COUNTIF(清单!$D$2:$D$490,"不需要"))
A12: 关键项进度 | B12: =IFERROR(COUNTIFS(清单!$E$2:$E$490,"是",清单!$D$2:$D$490,"已完成")/MAX(1,COUNTIFS(清单!$E$2:$E$490,"是",清单!$D$2:$D$490,"<>不需要")),0)
A13: 关键项还差 | B13: =COUNTIFS(清单!$E$2:$E$490,"是",清单!$D$2:$D$490,"未完成")&" 条"
A14: 预算合计（折人民币） | B14: =SUMIFS(清单!$G$2:$G$490,清单!$H$2:$H$490,"SGD",清单!$D$2:$D$490,"<>不需要")*$B$6+SUMIFS(清单!$G$2:$G$490,清单!$H$2:$H$490,"CNY",清单!$D$2:$D$490,"<>不需要") | C14: 只统计填了金额、且没标「不需要」的条目
A15: 国内带 · 已装箱 | B15: =COUNTIFS(清单!$F$2:$F$490,"国内带",清单!$D$2:$D$490,"已完成")&" / "&COUNTIFS(清单!$F$2:$F$490,"国内带",清单!$D$2:$D$490,"<>不需要")
A16: 落地买 · 已买到 | B16: =COUNTIFS(清单!$F$2:$F$490,"落地买",清单!$D$2:$D$490,"已完成")&" / "&COUNTIFS(清单!$F$2:$F$490,"落地买",清单!$D$2:$D$490,"<>不需要") | C16: 带法为空的是「要办的事」，不是物品
A18: 分类进度
A19: 分类 | B19: 总数 | C19: 已完成 | D19: 不需要 | E19: 待办 | F19: 关键项待办 | G19: 完成率 | H19: 进度条 | I19: 预算 SGD | J19: 预算 CNY
A20: 证件与材料 | B20: =COUNTIF(清单!$A$2:$A$490,$A20) | C20: =COUNTIFS(清单!$A$2:$A$490,$A20,清单!$D$2:$D$490,"已完成") | D20: =COUNTIFS(清单!$A$2:$A$490,$A20,清单!$D$2:$D$490,"不需要") | E20: =COUNTIFS(清单!$A$2:$A$490,$A20,清单!$D$2:$D$490,"未完成") | F20: =COUNTIFS(清单!$A$2:$A$490,$A20,清单!$E$2:$E$490,"是",清单!$D$2:$D$490,"未完成") | G20: =IFERROR($C20/MAX(1,$B20-$D20),0) | H20: =REPT("■",ROUND($G20*10,0))&REPT("·",10-ROUND($G20*10,0)) | I20: =SUMIFS(清单!$G$2:$G$490,清单!$A$2:$A$490,$A20,清单!$H$2:$H$490,"SGD",清单!$D$2:$D$490,"<>不需要") | J20: =SUMIFS(清单!$G$2:$G$490,清单!$A$2:$A$490,$A20,清单!$H$2:$H$490,"CNY",清单!$D$2:$D$490,"<>不需要")
A21: 钱与银行 | B21: =COUNTIF(清单!$A$2:$A$490,$A21) | C21: =COUNTIFS(清单!$A$2:$A$490,$A21,清单!$D$2:$D$490,"已完成") | D21: =COUNTIFS(清单!$A$2:$A$490,$A21,清单!$D$2:$D$490,"不需要") | E21: =COUNTIFS(清单!$A$2:$A$490,$A21,清单!$D$2:$D$490,"未完成") | F21: =COUNTIFS(清单!$A$2:$A$490,$A21,清单!$E$2:$E$490,"是",清单!$D$2:$D$490,"未完成") | G21: =IFERROR($C21/MAX(1,$B21-$D21),0) | H21: =REPT("■",ROUND($G21*10,0))&REPT("·",10-ROUND($G21*10,0)) | I21: =SUMIFS(清单!$G$2:$G$490,清单!$A$2:$A$490,$A21,清单!$H$2:$H$490,"SGD",清单!$D$2:$D$490,"<>不需要") | J21: =SUMIFS(清单!$G$2:$G$490,清单!$A$2:$A$490,$A21,清单!$H$2:$H$490,"CNY",清单!$D$2:$D$490,"<>不需要")
A22: 住 · 租房 | B22: =COUNTIF(清单!$A$2:$A$490,$A22) | C22: =COUNTIFS(清单!$A$2:$A$490,$A22,清单!$D$2:$D$490,"已完成") | D22: =COUNTIFS(清单!$A$2:$A$490,$A22,清单!$D$2:$D$490,"不需要") | E22: =COUNTIFS(清单!$A$2:$A$490,$A22,清单!$D$2:$D$490,"未完成") | F22: =COUNTIFS(清单!$A$2:$A$490,$A22,清单!$E$2:$E$490,"是",清单!$D$2:$D$490,"未完成") | G22: =IFERROR($C22/MAX(1,$B22-$D22),0) | H22: =REPT("■",ROUND($G22*10,0))&REPT("·",10-ROUND($G22*10,0)) | I22: =SUMIFS(清单!$G$2:$G$490,清单!$A$2:$A$490,$A22,清单!$H$2:$H$490,"SGD",清单!$D$2:$D$490,"<>不需要") | J22: =SUMIFS(清单!$G$2:$G$490,清单!$A$2:$A$490,$A22,清单!$H$2:$H$490,"CNY",清单!$D$2:$D$490,"<>不需要")
A23: 住 · 床品家居 | B23: =COUNTIF(清单!$A$2:$A$490,$A23) | C23: =COUNTIFS(清单!$A$2:$A$490,$A23,清单!$D$2:$D$490,"已完成") | D23: =COUNTIFS(清单!$A$2:$A$490,$A23,清单!$D$2:$D$490,"不需要") | E23: =COUNTIFS(清单!$A$2:$A$490,$A23,清单!$D$2:$D$490,"未完成") | F23: =COUNTIFS(清单!$A$2:$A$490,$A23,清单!$E$2:$E$490,"是",清单!$D$2:$D$490,"未完成") | G23: =IFERROR($C23/MAX(1,$B23-$D23),0) | H23: =REPT("■",ROUND($G23*10,0))&REPT("·",10-ROUND($G23*10,0)) | I23: =SUMIFS(清单!$G$2:$G$490,清单!$A$2:$A$490,$A23,清单!$H$2:$H$490,"SGD",清单!$D$2:$D$490,"<>不需要") | J23: =SUMIFS(清单!$G$2:$G$490,清单!$A$2:$A$490,$A23,清单!$H$2:$H$490,"CNY",清单!$D$2:$D$490,"<>不需要")
A24: 住 · 清洁耗材 | B24: =COUNTIF(清单!$A$2:$A$490,$A24) | C24: =COUNTIFS(清单!$A$2:$A$490,$A24,清单!$D$2:$D$490,"已完成") | D24: =COUNTIFS(清单!$A$2:$A$490,$A24,清单!$D$2:$D$490,"不需要") | E24: =COUNTIFS(清单!$A$2:$A$490,$A24,清单!$D$2:$D$490,"未完成") | F24: =COUNTIFS(清单!$A$2:$A$490,$A24,清单!$E$2:$E$490,"是",清单!$D$2:$D$490,"未完成") | G24: =IFERROR($C24/MAX(1,$B24-$D24),0) | H24: =REPT("■",ROUND($G24*10,0))&REPT("·",10-ROUND($G24*10,0)) | I24: =SUMIFS(清单!$G$2:$G$490,清单!$A$2:$A$490,$A24,清单!$H$2:$H$490,"SGD",清单!$D$2:$D$490,"<>不需要") | J24: =SUMIFS(清单!$G$2:$G$490,清单!$A$2:$A$490,$A24,清单!$H$2:$H$490,"CNY",清单!$D$2:$D$490,"<>不需要")
A25: 电子与充电 | B25: =COUNTIF(清单!$A$2:$A$490,$A25) | C25: =COUNTIFS(清单!$A$2:$A$490,$A25,清单!$D$2:$D$490,"已完成") | D25: =COUNTIFS(清单!$A$2:$A$490,$A25,清单!$D$2:$D$490,"不需要") | E25: =COUNTIFS(清单!$A$2:$A$490,$A25,清单!$D$2:$D$490,"未完成") | F25: =COUNTIFS(清单!$A$2:$A$490,$A25,清单!$E$2:$E$490,"是",清单!$D$2:$D$490,"未完成") | G25: =IFERROR($C25/MAX(1,$B25-$D25),0) | H25: =REPT("■",ROUND($G25*10,0))&REPT("·",10-ROUND($G25*10,0)) | I25: =SUMIFS(清单!$G$2:$G$490,清单!$A$2:$A$490,$A25,清单!$H$2:$H$490,"SGD",清单!$D$2:$D$490,"<>不需要") | J25: =SUMIFS(清单!$G$2:$G$490,清单!$A$2:$A$490,$A25,清单!$H$2:$H$490,"CNY",清单!$D$2:$D$490,"<>不需要")
A26: 洗漱护肤 | B26: =COUNTIF(清单!$A$2:$A$490,$A26) | C26: =COUNTIFS(清单!$A$2:$A$490,$A26,清单!$D$2:$D$490,"已完成") | D26: =COUNTIFS(清单!$A$2:$A$490,$A26,清单!$D$2:$D$490,"不需要") | E26: =COUNTIFS(清单!$A$2:$A$490,$A26,清单!$D$2:$D$490,"未完成") | F26: =COUNTIFS(清单!$A$2:$A$490,$A26,清单!$E$2:$E$490,"是",清单!$D$2:$D$490,"未完成") | G26: =IFERROR($C26/MAX(1,$B26-$D26),0) | H26: =REPT("■",ROUND($G26*10,0))&REPT("·",10-ROUND($G26*10,0)) | I26: =SUMIFS(清单!$G$2:$G$490,清单!$A$2:$A$490,$A26,清单!$H$2:$H$490,"SGD",清单!$D$2:$D$490,"<>不需要") | J26: =SUMIFS(清单!$G$2:$G$490,清单!$A$2:$A$490,$A26,清单!$H$2:$H$490,"CNY",清单!$D$2:$D$490,"<>不需要")
A27: 穿 · 衣物鞋包 | B27: =COUNTIF(清单!$A$2:$A$490,$A27) | C27: =COUNTIFS(清单!$A$2:$A$490,$A27,清单!$D$2:$D$490,"已完成") | D27: =COUNTIFS(清单!$A$2:$A$490,$A27,清单!$D$2:$D$490,"不需要") | E27: =COUNTIFS(清单!$A$2:$A$490,$A27,清单!$D$2:$D$490,"未完成") | F27: =COUNTIFS(清单!$A$2:$A$490,$A27,清单!$E$2:$E$490,"是",清单!$D$2:$D$490,"未完成") | G27: =IFERROR($C27/MAX(1,$B27-$D27),0) | H27: =REPT("■",ROUND($G27*10,0))&REPT("·",10-ROUND($G27*10,0)) | I27: =SUMIFS(清单!$G$2:$G$490,清单!$A$2:$A$490,$A27,清单!$H$2:$H$490,"SGD",清单!$D$2:$D$490,"<>不需要") | J27: =SUMIFS(清单!$G$2:$G$490,清单!$A$2:$A$490,$A27,清单!$H$2:$H$490,"CNY",清单!$D$2:$D$490,"<>不需要")
A28: 药品医疗 | B28: =COUNTIF(清单!$A$2:$A$490,$A28) | C28: =COUNTIFS(清单!$A$2:$A$490,$A28,清单!$D$2:$D$490,"已完成") | D28: =COUNTIFS(清单!$A$2:$A$490,$A28,清单!$D$2:$D$490,"不需要") | E28: =COUNTIFS(清单!$A$2:$A$490,$A28,清单!$D$2:$D$490,"未完成") | F28: =COUNTIFS(清单!$A$2:$A$490,$A28,清单!$E$2:$E$490,"是",清单!$D$2:$D$490,"未完成") | G28: =IFERROR($C28/MAX(1,$B28-$D28),0) | H28: =REPT("■",ROUND($G28*10,0))&REPT("·",10-ROUND($G28*10,0)) | I28: =SUMIFS(清单!$G$2:$G$490,清单!$A$2:$A$490,$A28,清单!$H$2:$H$490,"SGD",清单!$D$2:$D$490,"<>不需要") | J28: =SUMIFS(清单!$G$2:$G$490,清单!$A$2:$A$490,$A28,清单!$H$2:$H$490,"CNY",清单!$D$2:$D$490,"<>不需要")
A29: 食 · 厨房调料 | B29: =COUNTIF(清单!$A$2:$A$490,$A29) | C29: =COUNTIFS(清单!$A$2:$A$490,$A29,清单!$D$2:$D$490,"已完成") | D29: =COUNTIFS(清单!$A$2:$A$490,$A29,清单!$D$2:$D$490,"不需要") | E29: =COUNTIFS(清单!$A$2:$A$490,$A29,清单!$D$2:$D$490,"未完成") | F29: =COUNTIFS(清单!$A$2:$A$490,$A29,清单!$E$2:$E$490,"是",清单!$D$2:$D$490,"未完成") | G29: =IFERROR($C29/MAX(1,$B29-$D29),0) | H29: =REPT("■",ROUND($G29*10,0))&REPT("·",10-ROUND($G29*10,0)) | I29: =SUMIFS(清单!$G$2:$G$490,清单!$A$2:$A$490,$A29,清单!$H$2:$H$490,"SGD",清单!$D$2:$D$490,"<>不需要") | J29: =SUMIFS(清单!$G$2:$G$490,清单!$A$2:$A$490,$A29,清单!$H$2:$H$490,"CNY",清单!$D$2:$D$490,"<>不需要")
A30: 文具与学习 | B30: =COUNTIF(清单!$A$2:$A$490,$A30) | C30: =COUNTIFS(清单!$A$2:$A$490,$A30,清单!$D$2:$D$490,"已完成") | D30: =COUNTIFS(清单!$A$2:$A$490,$A30,清单!$D$2:$D$490,"不需要") | E30: =COUNTIFS(清单!$A$2:$A$490,$A30,清单!$D$2:$D$490,"未完成") | F30: =COUNTIFS(清单!$A$2:$A$490,$A30,清单!$E$2:$E$490,"是",清单!$D$2:$D$490,"未完成") | G30: =IFERROR($C30/MAX(1,$B30-$D30),0) | H30: =REPT("■",ROUND($G30*10,0))&REPT("·",10-ROUND($G30*10,0)) | I30: =SUMIFS(清单!$G$2:$G$490,清单!$A$2:$A$490,$A30,清单!$H$2:$H$490,"SGD",清单!$D$2:$D$490,"<>不需要") | J30: =SUMIFS(清单!$G$2:$G$490,清单!$A$2:$A$490,$A30,清单!$H$2:$H$490,"CNY",清单!$D$2:$D$490,"<>不需要")
A31: 行 · 机票行李 | B31: =COUNTIF(清单!$A$2:$A$490,$A31) | C31: =COUNTIFS(清单!$A$2:$A$490,$A31,清单!$D$2:$D$490,"已完成") | D31: =COUNTIFS(清单!$A$2:$A$490,$A31,清单!$D$2:$D$490,"不需要") | E31: =COUNTIFS(清单!$A$2:$A$490,$A31,清单!$D$2:$D$490,"未完成") | F31: =COUNTIFS(清单!$A$2:$A$490,$A31,清单!$E$2:$E$490,"是",清单!$D$2:$D$490,"未完成") | G31: =IFERROR($C31/MAX(1,$B31-$D31),0) | H31: =REPT("■",ROUND($G31*10,0))&REPT("·",10-ROUND($G31*10,0)) | I31: =SUMIFS(清单!$G$2:$G$490,清单!$A$2:$A$490,$A31,清单!$H$2:$H$490,"SGD",清单!$D$2:$D$490,"<>不需要") | J31: =SUMIFS(清单!$G$2:$G$490,清单!$A$2:$A$490,$A31,清单!$H$2:$H$490,"CNY",清单!$D$2:$D$490,"<>不需要")
... A36: 不建议带 | B36: =COUNTIF(清单!$A$2:$A$490,$A36) | C36: =COUNTIFS(清单!$A$2:$A$490,$A36,清单!$D$2:$D$490,"已完成") | D36: =COUNTIFS(清单!$A$2:$A$490,$A36,清单!$D$2:$D$490,"不需要") | E36: =COUNTIFS(清单!$A$2:$A$490,$A36,清单!$D$2:$D$490,"未完成") | F36: =COUNTIFS(清单!$A$2:$A$490,$A36,清单!$E$2:$E$490,"是",清单!$D$2:$D$490,"未完成") | G36: =IFERROR($C36/MAX(1,$B36-$D36),0) | H36: =REPT("■",ROUND($G36*10,0))&REPT("·",10-ROUND($G36*10,0)) | I36: =SUMIFS(清单!$G$2:$G$490,清单!$A$2:$A$490,$A36,清单!$H$2:$H$490,"SGD",清单!$D$2:$D$490,"<>不需要") | J36: =SUMIFS(清单!$G$2:$G$490,清单!$A$2:$A$490,$A36,清单!$H$2:$H$490,"CNY",清单!$D$2:$D$490,"<>不需要")
A37: 合计 | B37: =SUM(B20:B36) | C37: =SUM(C20:C36) | D37: =SUM(D20:D36) | E37: =SUM(E20:E36) | F37: =SUM(F20:F36) | G37: =IFERROR($C37/MAX(1,$B37-$D37),0) | H37: =REPT("■",ROUND($G37*10,0))&REPT("·",10-ROUND($G37*10,0)) | I37: =SUM(I20:I36) | J37: =SUM(J20:J36)
A39: 阶段时间轴（日期跟着 B5 出发日自动算）
A40: 阶段 | B40: 起 | C40: 止 | D40: 这一段要干的事 | E40: 条目 | F40: 已完成 | G40: 待办 | H40: 关键项待办 | I40: 完成率
A41: T-60+ 两个月前 | B41: 越早越好 | C41: =$B$5+-31 | D41: 搞定录取、签证、租房定位 | E41: =COUNTIF(清单!$B$2:$B$490,$A41) | F41: =COUNTIFS(清单!$B$2:$B$490,$A41,清单!$D$2:$D$490,"已完成") | G41: =COUNTIFS(清单!$B$2:$B$490,$A41,清单!$D$2:$D$490,"未完成") | H41: =COUNTIFS(清单!$B$2:$B$490,$A41,清单!$E$2:$E$490,"是",清单!$D$2:$D$490,"未完成") | I41: =IFERROR($F41/MAX(1,$E41-COUNTIFS(清单!$B$2:$B$490,$A41,清单!$D$2:$D$490,"不需要")),0)
A42: T-30 一个月前 | B42: =$B$5+-30 | C42: =$B$5+-8 | D42: STP、体检、机票、看房 | E42: =COUNTIF(清单!$B$2:$B$490,$A42) | F42: =COUNTIFS(清单!$B$2:$B$490,$A42,清单!$D$2:$D$490,"已完成") | G42: =COUNTIFS(清单!$B$2:$B$490,$A42,清单!$D$2:$D$490,"未完成") | H42: =COUNTIFS(清单!$B$2:$B$490,$A42,清单!$E$2:$E$490,"是",清单!$D$2:$D$490,"未完成") | I42: =IFERROR($F42/MAX(1,$E42-COUNTIFS(清单!$B$2:$B$490,$A42,清单!$D$2:$D$490,"不需要")),0)
A43: T-7 出发前一周 | B43: =$B$5+-7 | C43: =$B$5+-1 | D43: 收行李、国内收尾 | E43: =COUNTIF(清单!$B$2:$B$490,$A43) | F43: =COUNTIFS(清单!$B$2:$B$490,$A43,清单!$D$2:$D$490,"已完成") | G43: =COUNTIFS(清单!$B$2:$B$490,$A43,清单!$D$2:$D$490,"未完成") | H43: =COUNTIFS(清单!$B$2:$B$490,$A43,清单!$E$2:$E$490,"是",清单!$D$2:$D$490,"未完成") | I43: =IFERROR($F43/MAX(1,$E43-COUNTIFS(清单!$B$2:$B$490,$A43,清单!$D$2:$D$490,"不需要")),0)
A44: D-DAY 出发当天 | B44: =$B$5+0 | C44: =$B$5+0 | D44: 随身件、漫游、落地准备 | E44: =COUNTIF(清单!$B$2:$B$490,$A44) | F44: =COUNTIFS(清单!$B$2:$B$490,$A44,清单!$D$2:$D$490,"已完成") | G44: =COUNTIFS(清单!$B$2:$B$490,$A44,清单!$D$2:$D$490,"未完成") | H44: =COUNTIFS(清单!$B$2:$B$490,$A44,清单!$E$2:$E$490,"是",清单!$D$2:$D$490,"未完成") | I44: =IFERROR($F44/MAX(1,$E44-COUNTIFS(清单!$B$2:$B$490,$A44,清单!$D$2:$D$490,"不需要")),0)
A45: D+0 落地 48h | B45: =$B$5+0 | C45: =$B$5+2 | D45: 手机卡、交通卡、验房、采买 | E45: =COUNTIF(清单!$B$2:$B$490,$A45) | F45: =COUNTIFS(清单!$B$2:$B$490,$A45,清单!$D$2:$D$490,"已完成") | G45: =COUNTIFS(清单!$B$2:$B$490,$A45,清单!$D$2:$D$490,"未完成") | H45: =COUNTIFS(清单!$B$2:$B$490,$A45,清单!$E$2:$E$490,"是",清单!$D$2:$D$490,"未完成") | I45: =IFERROR($F45/MAX(1,$E45-COUNTIFS(清单!$B$2:$B$490,$A45,清单!$D$2:$D$490,"不需要")),0)
A46: W1 第一周 | B46: =$B$5+1 | C46: =$B$5+7 | D46: STP、Singpass、银行卡、注册 | E46: =COUNTIF(清单!$B$2:$B$490,$A46) | F46: =COUNTIFS(清单!$B$2:$B$490,$A46,清单!$D$2:$D$490,"已完成") | G46: =COUNTIFS(清单!$B$2:$B$490,$A46,清单!$D$2:$D$490,"未完成") | H46: =COUNTIFS(清单!$B$2:$B$490,$A46,清单!$E$2:$E$490,"是",清单!$D$2:$D$490,"未完成") | I46: =IFERROR($F46/MAX(1,$E46-COUNTIFS(清单!$B$2:$B$490,$A46,清单!$D$2:$D$490,"不需要")),0)
A47: M1 第一个月 | B47: =$B$5+8 | C47: =$B$5+30 | D47: 长期号、选课、安顿 | E47: =COUNTIF(清单!$B$2:$B$490,$A47) | F47: =COUNTIFS(清单!$B$2:$B$490,$A47,清单!$D$2:$D$490,"已完成") | G47: =COUNTIFS(清单!$B$2:$B$490,$A47,清单!$D$2:$D$490,"未完成") | H47: =COUNTIFS(清单!$B$2:$B$490,$A47,清单!$E$2:$E$490,"是",清单!$D$2:$D$490,"未完成") | I47: =IFERROR($F47/MAX(1,$E47-COUNTIFS(清单!$B$2:$B$490,$A47,清单!$D$2:$D$490,"不需要")),0)
A50: 怎么用
A51: 1. 「清单」表是主表。状态那一列点开下拉框选：未完成 / 已完成 / 不需要。选「不需要」的条目不算进进度和预算。
A52: 2. 要加自己的条目：直接写在「清单」表已有内容下面的空白行里（已经预留 100 行，下拉框和格式都做好了）。分类和阶段也用下拉框选，选了才会统计进这张总览。
A53: 3. 要填预算：在「清单」的「预算」列填数字，「币种」列选 SGD 或 CNY。总览和「预算」表会自动汇总。
A54: 4. 黄色格子（B5 出发日、B6 汇率）是唯一需要你手填的设置项，其余格子都是公式，别覆盖。
A55: 5. 「说明与来源」表里写了每个数字的出处、抓取日期，以及哪些是我推断的、哪些待核实。

Sheet 清单
A1: 分类 | B1: 阶段 | C1: 事项 | D1: 状态 | E1: 关键 | F1: 带法 | G1: 预算 | H1: 币种 | I1: 说明 / 出处 | J1: 我的备注
A2: 证件与材料 | B2: T-60+ 两个月前 | C2: 护照 —— 有效期 ≥6 个月且覆盖整个课程 | D2: 未完成 | E2: 是 | I2: 过期太早会压缩 STP 时长，来不及就先换新
A3: 证件与材料 | B3: T-30 一个月前 | C3: 护照首页 + 签证页 各复印 5 份 | D3: 未完成 | E3: 是 | F3: 国内带 | I3: NTU 注册、办 STP 时反复用到（小红书 @杂菜饭主理人「25fall新硕留子の开学清单」868赞，NTU 专属，2026-09）
A4: 证件与材料 | B4: T-30 一个月前 | C4: 护照电子版存云盘 + 手机相册 | D4: 未完成 | E4: 是
A5: 证件与材料 | B5: T-30 一个月前 | C5: IPA Letter：原件 + 复印件 3 份 | D5: 未完成 | E5: 是 | F5: 国内带 | I5: 入境时要出示，到校办 STP 必须提交。IPA 自带单次入境签证，不用另外办签证（小红书 @杂菜饭主理人「25fall新硕留子の开学清单」868赞，NTU 专属，2026-09）
A6: 证件与材料 | B6: T-30 一个月前 | C6: 录取通知书：PDF 原件 + 打印 2 份 | D6: 未完成 | E6: 是 | F6: 国内带 | I6: NTU 注册、租房、银行开户都可能要它证明身份
A7: 证件与材料 | B7: T-30 一个月前 | C7: 本科毕业证 + 学位证 原件 | D7: 未完成 | E7: 是 | F7: 国内带
A8: 证件与材料 | B8: T-30 一个月前 | C8: 毕业证学位证 英文公证件：原件 + 复印 2 份 | D8: 未完成 | E8: 是 | F8: 国内带 | I8: NTU 可能抽查，部分课程注册时需验证（小红书 @杂菜饭主理人「25fall新硕留子の开学清单」868赞，NTU 专属，2026-09）
A9: 证件与材料 | B9: T-30 一个月前 | C9: 本科成绩单：中英文原件 + 复印 2 份 | D9: 未完成 | E9: 是 | F9: 国内带 | I9: 要加盖学校公章，GPA 相关事项可能用到
A10: 证件与材料 | B10: T-30 一个月前 | C10: 雅思/托福成绩单：原件 + 复印 2 份 | D10: 未完成 | E10: 是 | F10: 国内带 | I10: NTU 部分学院注册时会核对
A11: 证件与材料 | B11: T-30 一个月前 | C11: 2 寸白底证件照 15 张（35×45mm）+ 电子版 | D11: 未完成 | E11: 是 | F11: 国内带 | G11: 60 | H11: CNY | I11: 学生证、银行卡、各种办理都要。校内拍约 15–20 新/组，国内提前拍划算得多（小红书 @杂菜饭主理人「25fall新硕留子の开学清单」868赞，NTU 专属，2026-09）
A12: 证件与材料 | B12: T-30 一个月前 | C12: 绒面小两寸证件照（OSE 用） | D12: 未完成 | F12: 国内带 | I12: 小红书 @krsttt「NUS j人留子 行前准备」733赞，2026-09 专门提到这个规格
A13: 证件与材料 | B13: T-30 一个月前 | C13: 1 寸证件照若干 | D13: 未完成 | F13: 国内带
A14: 证件与材料 | B14: T-60+ 两个月前 | C14: 学信网 / 学位网 英文认证报告 | D14: 未完成
A15: 证件与材料 | B15: T-30 一个月前 | C15: 身份证 + 复印件 | D15: 未完成 | E15: 是 | F15: 国内带
A16: 证件与材料 | B16: T-30 一个月前 | C16: 户口本复印件 | D16: 未完成 | F16: 国内带
A17: 证件与材料 | B17: T-7 出发前一周 | C17: 防水文件袋 ×2 | D17: 未完成 | E17: 是 | F17: 国内带 | I17: 证件分两袋装，一袋随身一袋托运，丢一个不至于全完（小红书 @杂菜饭主理人「25fall新硕留子の开学清单」868赞，NTU 专属，2026-09）
A18: 证件与材料 | B18: T-7 出发前一周 | C18: A4 文件夹 / 资料册 | D18: 未完成 | F18: 国内带
A19: 证件与材料 | B19: T-7 出发前一周 | C19: 紧急联系人纸质卡，放钱包 | D19: 未完成 | E19: 是 | F19: 国内带 | I19: 写清国内家人、NTU 导师/学院行政邮箱、国际学生办公室电话（小红书 @杂菜饭主理人「25fall新硕留子の开学清单」868赞，NTU 专属，2026-09）
A20: 证件与材料 | B20: T-7 出发前一周 | C20: 中国驻新加坡大使馆地址和电话记下来 | D20: 未完成
A21: 证件与材料 | B21: T-60+ 两个月前 | C21: 在 ICA SOLAR 提交 eForm 16 | D21: 未完成 | E21: 是 | I21: NTU 先把你的资料注册进 SOLAR；提交不早于开课前 2 个月（NTU 官网，2026-09-17）
A22: 证件与材料 | B22: T-60+ 两个月前 | C22: 缴 STP 申请处理费 S$45 | D22: 未完成 | E22: 是 | G22: 45 | H22: SGD | I22: 提交后 7 天内不缴，申请直接作废（NTU 官网，2026-09-17）
A23: 证件与材料 | B23: T-60+ 两个月前 | C23: 入学体检：HIV + 胸片 TB | D23: 未完成 | E23: 是 | I23: 课程超过 6 个月必做（NTU 官网，2026-09-17）
A24: 证件与材料 | B24: T-60+ 两个月前 | C24: 体检报告英文版交 Fullerton Health @NTU 认证 | D24: 未完成 | E24: 是 | G24: 32 | H24: SGD | I24: 国内做便宜；NTU 健康筛查本身 S$32（不含 GST），异常需加拍胸片 S$15（NTU 官网，2026-09-17）
A25: 证件与材料 | B25: T-30 一个月前 | C25: 把体检报告上传回 SOLAR，等 IPA | D25: 未完成 | E25: 是
A26: 证件与材料 | B26: T-30 一个月前 | C26: 缴 STP 签发费 S$60（+ 多次往返 S$30） | D26: 未完成 | E26: 是 | G26: 90 | H26: SGD | I26: 要不要多次往返看你会不会中途出境旅行（NTU 官网，2026-09-17）
A27: 证件与材料 | B27: T-30 一个月前 | C27: 在 ICA 官网预约 e-Appointment | D27: 未完成 | E27: 是 | I27: 只接受预约，walk-in 办不了（ICA 官网，2026-09-17）
A28: 证件与材料 | B28: T-7 出发前一周 | C28: 填 SG Arrival Card 电子入境卡 | D28: 未完成 | E28: 是 | I28: MyICA App，入境前 3 天内填
A29: 证件与材料 | B29: W1 第一周 | C29: 落地后按预约去 ICA 完成手续、录生物识别 | D29: 未完成 | E29: 是 | I29: 必须在短期访问准证或 IPA 有效期内完成，取早不取晚
A30: 证件与材料 | B30: W1 第一周 | C30: 办生物识别时手里要有能收短信的本地号 | D30: 未完成 | E30: 是 | I30: 没有的话要用授权代理人的号（NTU 官网，2026-09-17）
A31: 证件与材料 | B31: W1 第一周 | C31: 收到 ICA 登录邮件后用 Singpass 取电子学生准证 | D31: 未完成 | E31: 是 | I31: 一般生物识别后 7 个工作日内
A32: 证件与材料 | B32: T-30 一个月前 | C32: 疫苗接种记录英文版 | D32: 未完成 | F32: 国内带
A33: 证件与材料 | B33: T-30 一个月前 | C33: 驾照 + 英文公证件（可选） | D33: 未完成 | F33: 国内带
A34: 证件与材料 | B34: T-7 出发前一周 | C34: 打印机票行程单 | D34: 未完成 | F34: 国内带 | I34: 入境可能会问。@明天会下雨吗 说实际没用上，但打一份不占地方
A35: 证件与材料 | B35: T-7 出发前一周 | C35: 打印住宿证明 / 租约 | D35: 未完成 | E35: 是 | F35: 国内带
A36: 证件与材料 | B36: T-7 出发前一周 | C36: 保险单：电子版 + 打印一份 | D36: 未完成 | F36: 国内带
A37: 证件与材料 | B37: T-7 出发前一周 | C37: 所有证件扫描件存三处：手机、云盘、邮箱 | D37: 未完成 | E37: 是 | I37: 丢件时这一步能救命
A38: 钱与银行 | B38: T-7 出发前一周 | C38: 换现金 S$1000–1500，要 50/10/5 小面额 | D38: 未完成 | E38: 是 | G38: 1200 | H38: SGD | I38: 刚到付押金、买电话卡、吃饭都用现金，小面额方便找零（小红书 @杂菜饭主理人「25fall新硕留子の开学清单」868赞，NTU 专属，2026-09）。小红书 @krsttt「NUS j人留子 行前准备」733赞，2026-09 带了 1000 新
A39: 钱与银行 | B39: T-30 一个月前 | C39: 国内银联卡 1 张 | D39: 未完成 | E39: 是 | F39: 国内带 | I39: NTU 校内 ATM 支持银联取现，手续费约 1%–2%，应急用（小红书 @杂菜饭主理人「25fall新硕留子の开学清单」868赞，NTU 专属，2026-09）
A40: 钱与银行 | B40: T-30 一个月前 | C40: 国际信用卡 Visa/Mastercard 1 张 | D40: 未完成 | E40: 是 | F40: 国内带 | I40: 交学费、网购用，部分宿舍押金支持信用卡
A41: 钱与银行 | B41: T-30 一个月前 | C41: 国内卡开通境外消费/取现，调高单日限额 | D41: 未完成 | E41: 是 | I41: 出国前在手机银行里改掉
A42: 钱与银行 | B42: T-7 出发前一周 | C42: 记下国内银行的境外客服电话 | D42: 未完成 | I42: 卡被风控时能打
A43: 钱与银行 | B43: T-30 一个月前 | C43: 确认学费缴纳方式和截止日 | D43: 未完成 | E43: 是 | I43: 正式注册后约 2 周收到 NSS-Finance 账单（NTU 官网，2026-09-17）
A44: 钱与银行 | B44: T-30 一个月前 | C44: 比较跨境汇款渠道：中行跨境通 / Wise / 电汇 | D44: 未完成 | I44: 手续费和汇率差距不小
A45: 钱与银行 | B45: T-30 一个月前 | C45: 中国银行新加坡卡（可选，国内可预约） | D45: 未完成 | I45: 搭配国内中行跨境转账免手续费
A46: 钱与银行 | B46: W1 第一周 | C46: 落地办 DBS/POSB 学生账户 | D46: 未完成 | E46: 是 | I46: 全日制学生且 29 岁以下可免 S$2/月管理费；可提前线上预申请
A47: 钱与银行 | B47: M1 第一个月 | C47: OCBC 或 UOB 作备用（可选） | D47: 未完成
A48: 钱与银行 | B48: W1 第一周 | C48: 绑定 PayNow / PayLah | D48: 未完成 | E48: 是 | I48: 本地转账、AA 制、付房租都靠它
A49: 钱与银行 | B49: T-30 一个月前 | C49: 准备押金 + 首月房租 | D49: 未完成 | E49: 是 | G49: 2500 | H49: SGD | I49: 押金普遍 1–1.5 个月租金
A50: 钱与银行 | B50: T-30 一个月前 | C50: 建一个留学预算表，按月记账 | D50: 未完成
A51: 钱与银行 | B51: T-30 一个月前 | C51: 确认 NTU 学生保险覆盖范围 | D51: 未完成
A52: 钱与银行 | B52: T-30 一个月前 | C52: 补充医疗险 / 行李险（可选） | D52: 未完成
A53: 钱与银行 | B53: T-7 出发前一周 | C53: 小钱包 + 大钱包 | D53: 未完成 | F53: 国内带 | I53: 小红书 @krsttt「NUS j人留子 行前准备」733赞，2026-09 两个都带了
A54: 钱与银行 | B54: T-7 出发前一周 | C54: 卡套（学生证、交通卡） | D54: 未完成 | F54: 国内带
A55: 钱与银行 | B55: T-30 一个月前 | C55: 支付宝/微信绑好还能用的支付方式 | D55: 未完成 | E55: 是
A56: 住 · 租房 | B56: T-60+ 两个月前 | C56: 先定区域：Pioneer / Boon Lay / Jurong West / Lakeside / Clementi | D56: 未完成 | E56: 是 | I56: 越靠近绿线西段越省通勤
A57: 住 · 租房 | B57: T-60+ 两个月前 | C57: 硬指标：到 NTU 校车站或 179/199 巴士站步行 ≤5 分钟 | D57: 未完成 | E57: 是 | I57: 这条比房子新旧重要得多
A58: 住 · 租房 | B58: T-60+ 两个月前 | C58: 房源渠道铺开：PropertyGuru、99.co、SRX、Carousell、小红书、学长群 | D58: 未完成
A59: 住 · 租房 | B59: T-60+ 两个月前 | C59: 避坑：Westwood、Floravale 一带 | D59: 未完成 | E59: 是 | I59: 有住户实录：要走 700–800m 到唯一直达的 199 站，社区巴士班次少挤不上，打车回去十几新（小红书 @夏芽儿「别租Westwood」241赞，2026-09）。属个人经历，自己再核
A60: 住 · 租房 | B60: T-60+ 两个月前 | C60: 想清楚组屋 vs 公寓 | D60: 未完成 | I60: 组屋便宜、楼下就是食阁巴刹；公寓有泳池健身房但贵，且不一定用得上
A61: 住 · 租房 | B61: T-60+ 两个月前 | C61: 摸清价格区间 | D61: 未完成 | I61: 小红书 2026-09 挂牌：Jurong West 普通房约 S$900/月、Lakeside 2B2B 次卧约 S$1900/月不含 bills。单套报价，不代表均价
A62: 住 · 租房 | B62: T-30 一个月前 | C62: 线上看房要求房东实拍通勤路线 | D62: 未完成 | E62: 是 | I62: 不要只看地图直线距离
A63: 住 · 租房 | B63: T-30 一个月前 | C63: 核验房东身份，确认 HDB 出租已获批准 | D63: 未完成 | E63: 是
A64: 住 · 租房 | B64: T-30 一个月前 | C64: 合同逐条看 | D64: 未完成 | E64: 是 | I64: 租期、押金、agent fee、水电网谁付、能否煮饭、访客规定、提前退租罚则
A65: 住 · 租房 | B65: T-30 一个月前 | C65: 确认「包不包 bills」 | D65: 未完成 | I65: 水电网燃气差价一个月可能几十上百新
A66: 住 · 租房 | B66: T-30 一个月前 | C66: 问清楚洗衣机/烘干机：有没有、洗一次多少钱 | D66: 未完成
A67: 住 · 租房 | B67: T-30 一个月前 | C67: 问清楚房间里有没有床、床垫、衣柜、书桌、空调 | D67: 未完成 | E67: 是 | I67: unfurnished 的房间要自己买家具，成本差很多
A68: 住 · 租房 | B68: T-30 一个月前 | C68: 量一下床的尺寸再买床品 | D68: 未完成 | E68: 是 | I68: 本地单人床多为 90cm×190cm（小红书 @杂菜饭主理人「25fall新硕留子の开学清单」868赞，NTU 专属，2026-09）
A69: 住 · 租房 | B69: T-30 一个月前 | C69: 确认插座类型和数量 | D69: 未完成 | I69: 英标三方扁头，230V/50Hz
A70: 住 · 租房 | B70: T-60+ 两个月前 | C70: 找室友：性别、作息、卫生习惯、公摊怎么算 提前讲清 | D70: 未完成
A71: 住 · 租房 | B71: T-30 一个月前 | C71: 备选方案：先订 3–7 天短租/酒店，落地线下看房再签 | D71: 未完成 | I71: 不确定就别在国内签死
A72: 住 · 租房 | B72: D+0 落地 48h | C72: 入住验房：拍视频 + 照片存证，家具电器逐件测试 | D72: 未完成 | E72: 是 | I72: 搬走时退押金全靠这些
A73: 住 · 租房 | B73: D+0 落地 48h | C73: 留存押金收据 / 转账凭证 | D73: 未完成 | E73: 是
A74: 住 · 租房 | B74: D+0 落地 48h | C74: 要 WiFi 密码、电箱和水阀位置 | D74: 未完成
A75: 住 · 床品家居 | B75: T-7 出发前一周 | C75: 床单 ×1–2 | D75: 未完成 | F75: 国内带 | I75: 确认床尺寸后再买，本地单人床多为 90×190cm；也可落地在 IKEA 或 Courts 买（小红书 @杂菜饭主理人「25fall新硕留子の开学清单」868赞，NTU 专属，2026-09）
A76: 住 · 床品家居 | B76: T-7 出发前一周 | C76: 被套 ×1–2 | D76: 未完成 | F76: 国内带
A77: 住 · 床品家居 | B77: T-7 出发前一周 | C77: 枕套 ×2 | D77: 未完成 | F77: 国内带
A78: 住 · 床品家居 | B78: T-7 出发前一周 | C78: 床垫罩 / 保护垫 | D78: 未完成 | F78: 国内带 | I78: 小红书 @krsttt「NUS j人留子 行前准备」733赞，2026-09 列了
A79: 住 · 床品家居 | B79: T-7 出发前一周 | C79: 夏凉被 / 空调被 ×1 | D79: 未完成 | E79: 是 | F79: 国内带 | I79: 室内空调开得很低，但不需要厚被子
A80: 住 · 床品家居 | B80: T-7 出发前一周 | C80: 枕头 | D80: 未完成 | F80: 国内带 | I80: 小红书 @明天会下雨吗？「新加坡留学之什么真的该带」576赞，2026-09：这边枕头贵且不好睡，对枕头有要求的一定自己带
A81: 住 · 床品家居 | B81: T-7 出发前一周 | C81: 遮光眼罩 | D81: 未完成 | F81: 国内带
A82: 住 · 床品家居 | B82: T-7 出发前一周 | C82: 耳塞 | D82: 未完成 | F82: 国内带
A83: 住 · 床品家居 | B83: T-7 出发前一周 | C83: 毛巾 ×2 / 速干毛巾 | D83: 未完成 | F83: 国内带 | I83: 小红书 @明天会下雨吗？「新加坡留学之什么真的该带」576赞，2026-09 推荐速干款
A84: 住 · 床品家居 | B84: T-7 出发前一周 | C84: 浴巾 ×1 | D84: 未完成 | F84: 国内带
A85: 住 · 床品家居 | B85: T-7 出发前一周 | C85: 折叠晾衣架 ×10 | D85: 未完成 | F85: 国内带 | I85: 小红书 @杂菜饭主理人「25fall新硕留子の开学清单」868赞，NTU 专属，2026-09：宿舍晾衣空间有限，折叠款方便收纳。但 小红书 @明天会下雨吗？「新加坡留学之什么真的该带」576赞，2026-09 认为不用带，本地 1 新约 12 个 —— 自己权衡
A86: 住 · 床品家居 | B86: T-7 出发前一周 | C86: 裤架 / 晾衣夹 | D86: 未完成 | F86: 落地买
A87: 住 · 床品家居 | B87: T-7 出发前一周 | C87: 台灯 | D87: 未完成 | F87: 国内带
A88: 住 · 床品家居 | B88: T-7 出发前一周 | C88: 手持小风扇 | D88: 未完成 | F88: 国内带 | I88: 小红书 @明天会下雨吗？「新加坡留学之什么真的该带」576赞，2026-09：好用！有用！
A89: 住 · 床品家居 | B89: D+0 落地 48h | C89: 除湿盒 / 干燥剂 | D89: 未完成 | F89: 落地买 | I89: 常年高湿，衣柜容易发霉
A90: 住 · 床品家居 | B90: T-7 出发前一周 | C90: 防霉贴 / 樟脑丸 | D90: 未完成 | F90: 国内带
A91: 住 · 床品家居 | B91: T-7 出发前一周 | C91: 电蚊香 / 驱蚊液 / 无比滴 | D91: 未完成 | E91: 是 | F91: 国内带 | I91: 新加坡有登革热，别省这个。小红书 @krsttt「NUS j人留子 行前准备」733赞，2026-09 带了无比滴
A92: 住 · 床品家居 | B92: T-7 出发前一周 | C92: 衣物收纳箱 / 收纳袋 | D92: 未完成 | F92: 落地买
A93: 住 · 床品家居 | B93: T-7 出发前一周 | C93: 真空压缩袋 | D93: 未完成 | F93: 国内带 | I93: 能省不少行李空间
A94: 住 · 床品家居 | B94: T-7 出发前一周 | C94: 免钉挂钩 | D94: 未完成 | F94: 国内带
A95: 住 · 床品家居 | B95: T-7 出发前一周 | C95: 化妆镜 / 小镜子 | D95: 未完成 | F95: 国内带 | I95: 小红书 @明天会下雨吗？「新加坡留学之什么真的该带」576赞，2026-09 推荐带一个
A96: 住 · 床品家居 | B96: D+0 落地 48h | C96: 门后挂架 / 置物架 | D96: 未完成 | F96: 落地买
A97: 住 · 床品家居 | B97: D+0 落地 48h | C97: 折叠小桌板（可选） | D97: 未完成 | F97: 落地买
A98: 住 · 清洁耗材 | B98: T-7 出发前一周 | C98: 密封袋 大中小各一批 | D98: 未完成 | E98: 是 | F98: 国内带 | I98: 小红书 @frjinnfaerei「26fall行李进度50%」459赞，2026-09 自称「密封袋战神」，分装液体、收纳零碎全靠它
A99: 住 · 清洁耗材 | B99: T-7 出发前一周 | C99: 纸巾：大包 + 随身小包纸 | D99: 未完成 | F99: 国内带 | I99: 小红书 @frjinnfaerei「26fall行李进度50%」459赞，2026-09 带了一大包加很多小包
A100: 住 · 清洁耗材 | B100: T-7 出发前一周 | C100: 湿厕纸 | D100: 未完成 | F100: 国内带
...

Sheet 预算
A1: 预算估算
A2: 「预估」列是从「清单」表自动汇总的，改清单里的金额这里就跟着变。「实际花费」列自己填，用人民币。
A4: 分类 | B4: 预估 SGD | C4: 预估 CNY | D4: 预估合计（¥） | E4: 实际花费（¥） | F4: 差额（¥）
A5: 证件与材料 | B5: =SUMIFS(清单!$G$2:$G$490,清单!$A$2:$A$490,$A5,清单!$H$2:$H$490,"SGD",清单!$D$2:$D$490,"<>不需要") | C5: =SUMIFS(清单!$G$2:$G$490,清单!$A$2:$A$490,$A5,清单!$H$2:$H$490,"CNY",清单!$D$2:$D$490,"<>不需要") | D5: =$B5*总览!$B$6+$C5 | F5: =IF($E5="","",$E5-$D5)
A6: 钱与银行 | B6: =SUMIFS(清单!$G$2:$G$490,清单!$A$2:$A$490,$A6,清单!$H$2:$H$490,"SGD",清单!$D$2:$D$490,"<>不需要") | C6: =SUMIFS(清单!$G$2:$G$490,清单!$A$2:$A$490,$A6,清单!$H$2:$H$490,"CNY",清单!$D$2:$D$490,"<>不需要") | D6: =$B6*总览!$B$6+$C6 | F6: =IF($E6="","",$E6-$D6)
A7: 住 · 租房 | B7: =SUMIFS(清单!$G$2:$G$490,清单!$A$2:$A$490,$A7,清单!$H$2:$H$490,"SGD",清单!$D$2:$D$490,"<>不需要") | C7: =SUMIFS(清单!$G$2:$G$490,清单!$A$2:$A$490,$A7,清单!$H$2:$H$490,"CNY",清单!$D$2:$D$490,"<>不需要") | D7: =$B7*总览!$B$6+$C7 | F7: =IF($E7="","",$E7-$D7)
A8: 住 · 床品家居 | B8: =SUMIFS(清单!$G$2:$G$490,清单!$A$2:$A$490,$A8,清单!$H$2:$H$490,"SGD",清单!$D$2:$D$490,"<>不需要") | C8: =SUMIFS(清单!$G$2:$G$490,清单!$A$2:$A$490,$A8,清单!$H$2:$H$490,"CNY",清单!$D$2:$D$490,"<>不需要") | D8: =$B8*总览!$B$6+$C8 | F8: =IF($E8="","",$E8-$D8)
A9: 住 · 清洁耗材 | B9: =SUMIFS(清单!$G$2:$G$490,清单!$A$2:$A$490,$A9,清单!$H$2:$H$490,"SGD",清单!$D$2:$D$490,"<>不需要") | C9: =SUMIFS(清单!$G$2:$G$490,清单!$A$2:$A$490,$A9,清单!$H$2:$H$490,"CNY",清单!$D$2:$D$490,"<>不需要") | D9: =$B9*总览!$B$6+$C9 | F9: =IF($E9="","",$E9-$D9)
A10: 电子与充电 | B10: =SUMIFS(清单!$G$2:$G$490,清单!$A$2:$A$490,$A10,清单!$H$2:$H$490,"SGD",清单!$D$2:$D$490,"<>不需要") | C10: =SUMIFS(清单!$G$2:$G$490,清单!$A$2:$A$490,$A10,清单!$H$2:$H$490,"CNY",清单!$D$2:$D$490,"<>不需要") | D10: =$B10*总览!$B$6+$C10 | F10: =IF($E10="","",$E10-$D10)
A11: 洗漱护肤 | B11: =SUMIFS(清单!$G$2:$G$490,清单!$A$2:$A$490,$A11,清单!$H$2:$H$490,"SGD",清单!$D$2:$D$490,"<>不需要") | C11: =SUMIFS(清单!$G$2:$G$490,清单!$A$2:$A$490,$A11,清单!$H$2:$H$490,"CNY",清单!$D$2:$D$490,"<>不需要") | D11: =$B11*总览!$B$6+$C11 | F11: =IF($E11="","",$E11-$D11)
A12: 穿 · 衣物鞋包 | B12: =SUMIFS(清单!$G$2:$G$490,清单!$A$2:$A$490,$A12,清单!$H$2:$H$490,"SGD",清单!$D$2:$D$490,"<>不需要") | C12: =SUMIFS(清单!$G$2:$G$490,清单!$A$2:$A$490,$A12,清单!$H$2:$H$490,"CNY",清单!$D$2:$D$490,"<>不需要") | D12: =$B12*总览!$B$6+$C12 | F12: =IF($E12="","",$E12-$D12)
A13: 药品医疗 | B13: =SUMIFS(清单!$G$2:$G$490,清单!$A$2:$A$490,$A13,清单!$H$2:$H$490,"SGD",清单!$D$2:$D$490,"<>不需要") | C13: =SUMIFS(清单!$G$2:$G$490,清单!$A$2:$A$490,$A13,清单!$H$2:$H$490,"CNY",清单!$D$2:$D$490,"<>不需要") | D13: =$B13*总览!$B$6+$C13 | F13: =IF($E13="","",$E13-$D13)
A14: 食 · 厨房调料 | B14: =SUMIFS(清单!$G$2:$G$490,清单!$A$2:$A$490,$A14,清单!$H$2:$H$490,"SGD",清单!$D$2:$D$490,"<>不需要") | C14: =SUMIFS(清单!$G$2:$G$490,清单!$A$2:$A$490,$A14,清单!$H$2:$H$490,"CNY",清单!$D$2:$D$490,"<>不需要") | D14: =$B14*总览!$B$6+$C14 | F14: =IF($E14="","",$E14-$D14)
A15: 文具与学习 | B15: =SUMIFS(清单!$G$2:$G$490,清单!$A$2:$A$490,$A15,清单!$H$2:$H$490,"SGD",清单!$D$2:$D$490,"<>不需要") | C15: =SUMIFS(清单!$G$2:$G$490,清单!$A$2:$A$490,$A15,清单!$H$2:$H$490,"CNY",清单!$D$2:$D$490,"<>不需要") | D15: =$B15*总览!$B$6+$C15 | F15: =IF($E15="","",$E15-$D15)
A16: 行 · 机票行李 | B16: =SUMIFS(清单!$G$2:$G$490,清单!$A$2:$A$490,$A16,清单!$H$2:$H$490,"SGD",清单!$D$2:$D$490,"<>不需要") | C16: =SUMIFS(清单!$G$2:$G$490,清单!$A$2:$A$490,$A16,清单!$H$2:$H$490,"CNY",清单!$D$2:$D$490,"<>不需要") | D16: =$B16*总览!$B$6+$C16 | F16: =IF($E16="","",$E16-$D16)
... A21: 不建议带 | B21: =SUMIFS(清单!$G$2:$G$490,清单!$A$2:$A$490,$A21,清单!$H$2:$H$490,"SGD",清单!$D$2:$D$490,"<>不需要") | C21: =SUMIFS(清单!$G$2:$G$490,清单!$A$2:$A$490,$A21,清单!$H$2:$H$490,"CNY",清单!$D$2:$D$490,"<>不需要") | D21: =$B21*总览!$B$6+$C21 | F21: =IF($E21="","",$E21-$D21)
A22: 合计 | B22: =SUM(B5:B21) | C22: =SUM(C5:C21) | D22: =SUM(D5:D21) | E22: =SUM(E5:E21) | F22: =SUM(F5:F21)
A24: 预估里没有包含的大头，自己按实际情况加到「清单」表里：
A25: · 学费 —— 以 NTU 录取邮件 / NSS-Finance 账单为准
A26: · 机票 —— 以你实际买的为准
A27: · 每月房租 × 租期 —— 清单里只填了「押金 + 首月」，长期租金要单独算
A28: · 日常伙食、交通、话费的月度开销
A30: 已填的参考金额出处见「说明与来源」表，抓取日期 2026-09-17，费用和政策会变，出发前以官网为准。

Sheet 说明与来源
B2: 说明与来源
B3: 抓取日期：2026-09-17。费用和政策会变，出发前请以 NTU / ICA 官网和你自己收到的邮件通知为准。
B5: 一、这份表里哪些是推断的
B6: · 出发日期默认 2026-11-01：你说的是「11 intake」，我按 2026 年 11 月入学推的，不是你给的日期。在「总览」B5 改成真实出发日。
B7: · 汇率默认 1 SGD = 5.40 CNY：非实时，待核实。在「总览」B6 改。
B8: · 「国内带 / 落地买」的标注来自留学生攻略帖的普遍说法，是个人经验汇总，不是硬规则。
B9: · 租金区间（Jurong West 普通房约 S$900/月、Lakeside 2B2B 次卧约 S$1900/月）是 2026-09 小红书上的单套挂牌价，不代表市场均价。
B11: 二、哪些还需要你自己核实
B12: · 「红线 · 别带」整栏（口香糖、电子烟、含麻黄碱/可待因的药、含濒危成分中成药、肉制品）来自中文攻略汇总，我没有逐条从官网核对。这一栏后果最重，出发前请上 Singapore Customs（customs.gov.sg）和 HSA（hsa.gov.sg）官网再确认。
B13: · 过滤花洒是否必要：攻略里高频推荐，说新加坡水质偏硬，但效果因人而异，待核实。
B14: · 航司行李额（东航 23kg/件、加一件约 800 元人民币）是 2026-09 某篇留学生记录，以你实际购买的航司条款为准。
B16: 三、官方来源
... B45: 直接写到「清单」表已有内容下面的空白行里（淡黄色那些行），分类、阶段、状态都用下拉框选。示例：
B47: 示例行（照这个格式填，这张表只是演示，不参与统计） | C47: 分类 | D47: 阶段 | E47: 事项 | F47: 状态 | G47: 关键 | H47: 带法 | I47: 预算 | J47: 币种 | K47: 说明 / 出处 | L47: 我的备注
C48: 行 · 机票行李 | D48: T-7 出发前一周 | E48: 买一个行李秤 | F48: 未完成 | H48: 国内带 | I48: 60 | J48: CNY | L48: 出发前一晚称一遍
